{"nm":"Main Scene","ddd":0,"h":512,"w":512,"meta":{"g":"@lottiefiles/creator 1.75.0"},"layers":[{"ty":2,"nm":"3","sr":1,"st":0,"op":35,"ip":0,"hd":false,"ddd":0,"bm":0,"hasMask":false,"ao":0,"ks":{"a":{"a":0,"k":[540.0000000000001,540.0000183694035]},"s":{"a":0,"k":[48,48]},"sk":{"a":0,"k":0},"p":{"a":0,"k":[279.58577482955593,252.80002494040207]},"r":{"a":1,"k":[{"o":{"x":0,"y":0},"i":{"x":0.36,"y":1},"s":[-117],"t":0},{"o":{"x":0.65,"y":0},"i":{"x":0.36,"y":1},"s":[0],"t":11},{"o":{"x":0.65,"y":0},"i":{"x":0.36,"y":1},"s":[0],"t":15},{"s":[-117],"t":28}]},"sa":{"a":0,"k":0},"o":{"a":1,"k":[{"o":{"x":0.167,"y":0.167},"i":{"x":0.833,"y":0.833},"s":[0],"t":4},{"o":{"x":0,"y":0},"i":{"x":1,"y":1},"s":[100],"t":11},{"o":{"x":0.167,"y":0.167},"i":{"x":0.833,"y":0.833},"s":[100],"t":15},{"s":[0],"t":23}]}},"refId":"3_ae60e737-ebb3-4bd5-8835-11905e108d8c","ind":1},{"ty":2,"nm":"2","sr":1,"st":0,"op":35,"ip":0,"hd":false,"ddd":0,"bm":0,"hasMask":false,"ao":0,"ks":{"a":{"a":0,"k":[539.9999999999999,540.0000149954316]},"s":{"a":0,"k":[48,48]},"sk":{"a":0,"k":0},"p":{"a":0,"k":[255.99999999999994,256.0000071978072]},"r":{"a":0,"k":0},"sa":{"a":0,"k":0},"o":{"a":0,"k":100}},"refId":"2_4b63997d-2330-41ac-b853-62fddd03f811","ind":2},{"ty":2,"nm":"1","sr":1,"st":0,"op":35,"ip":0,"hd":false,"ddd":0,"bm":0,"hasMask":false,"ao":0,"ks":{"a":{"a":0,"k":[539.9999999999999,540.0000149954316]},"s":{"a":0,"k":[48,48]},"sk":{"a":0,"k":0},"p":{"a":0,"k":[231.47079417726178,256.00000359890356]},"r":{"a":1,"k":[{"o":{"x":0.55,"y":0.06},"i":{"x":0.36,"y":1},"s":[113],"t":0},{"o":{"x":0.65,"y":0},"i":{"x":0.36,"y":1},"s":[0],"t":11},{"o":{"x":0.65,"y":0},"i":{"x":0.36,"y":1},"s":[0],"t":15},{"s":[113],"t":28}]},"sa":{"a":0,"k":0},"o":{"a":1,"k":[{"o":{"x":0.167,"y":0.167},"i":{"x":0.833,"y":0.833},"s":[0],"t":4},{"o":{"x":0.55,"y":0.06},"i":{"x":1,"y":1},"s":[100],"t":11},{"o":{"x":0.55,"y":0.06},"i":{"x":1,"y":1},"s":[100],"t":15},{"s":[0],"t":23}]}},"refId":"1_ec92dc68-853b-439c-b5ae-2d513b0167a4","ind":3}],"v":"5.7.0","fr":30,"op":30,"ip":0,"assets":[{"id":"3_1629cc8f-4d6e-470b-a091-f7caf91d09e3","e":0,"w":1080,"h":1080,"p":"3_1629cc8f-4d6e-470b-a091-f7caf91d09e3.jpeg","u":"/i/"},{"id":"1_7b981b9a-18ac-44fb-b420-38b0fda41a00","e":0,"w":1080,"h":1080,"p":"1_7b981b9a-18ac-44fb-b420-38b0fda41a00.jpeg","u":"/i/"},{"id":"2_da2cdc4e-3524-4224-b987-965619a3e885","e":0,"w":1080,"h":1080,"p":"2_da2cdc4e-3524-4224-b987-965619a3e885.jpeg","u":"/i/"},{"id":"1_ec92dc68-853b-439c-b5ae-2d513b0167a4","e":0,"w":1080,"h":1080,"p":"1_ec92dc68-853b-439c-b5ae-2d513b0167a4.png","u":"/i/"},{"id":"2_4b63997d-2330-41ac-b853-62fddd03f811","e":0,"w":1080,"h":1080,"p":"2_4b63997d-2330-41ac-b853-62fddd03f811.png","u":"/i/"},{"id":"3_ae60e737-ebb3-4bd5-8835-11905e108d8c","e":0,"w":1080,"h":1080,"p":"3_ae60e737-ebb3-4bd5-8835-11905e108d8c.png","u":"/i/"}]}